gesys/__init__.py
gesys/preview.py
gesys/__pycache__/__init__.cpython-39.pyc
gesys/__pycache__/preview.cpython-39.pyc
gesys/detector/__init__.py
gesys/detector/detector.pyd
gesys/detector/m1.onnx
gesys/detector/m2.onnx
gesys/detector/utils.pyd
gesys/recognizer/__init__.py
gesys/recognizer/m3.onnx
gesys/recognizer/recognizer.pyd
gesys/runner/__init__.py
gesys/runner/hand_identifier.py
gesys/runner/runner.py
gesys-1.1.15.dist-info/METADATA
gesys-1.1.15.dist-info/WHEEL
gesys-1.1.15.dist-info/top_level.txt
gesys-1.1.15.dist-info/RECORD
